rich/.DS_Store
rich/tui/.DS_Store
rich/tui/_context.py
rich/tui/_timer.py
rich/tui/actions.py
rich/tui/app.py
rich/tui/case.py
rich/tui/driver.py
rich/tui/events.py
rich/tui/examples/simple.py
rich/tui/message.py
rich/tui/message_pump.py
rich/tui/scrollbar.py
rich/tui/types.py
rich/tui/view.py
rich/tui/widget.py
rich/tui/widgets/__init__.py
rich/tui/widgets/header.py
rich/tui/widgets/placeholder.py
rich/tui/widgets/window.py
rich.tui-0.1.0.dist-info/LICENSE
rich.tui-0.1.0.dist-info/WHEEL
rich.tui-0.1.0.dist-info/METADATA
rich.tui-0.1.0.dist-info/RECORD
